db_rb_util/common_utils.py
db_rb_util/db_connector.py
db_rb_util/logging_utils.py
db_rb_util/mongodb_utils.py
db_rb_util/s3_utils.py
tests/__init__.py
tests/common_resources.py
tests/test_common_utils.py
tests/test_db_connector.py
tests/test_mongodb_utils.py
tests/test_s3_utils.py
venv/bin/activate_this.py
venv/bin/jp.py
venv/bin/rst2html.py
venv/bin/rst2html4.py
venv/bin/rst2html5.py
venv/bin/rst2latex.py
venv/bin/rst2man.py
venv/bin/rst2odt.py
venv/bin/rst2odt_prepstyles.py
venv/bin/rst2pseudoxml.py
venv/bin/rst2s5.py
venv/bin/rst2xetex.py
venv/bin/rst2xml.py
venv/bin/rstpep2html.py
db_rb_util-0.0.2.dist-info/METADATA
db_rb_util-0.0.2.dist-info/WHEEL
db_rb_util-0.0.2.dist-info/top_level.txt
db_rb_util-0.0.2.dist-info/RECORD
